{
  "crecord_write_time": 1440685063,
  "enable": true,
  "crecord_type": "view",
  "crecord_creation_time": 0,
  "crecord_name": "notifications.json",
  "description": null,
  "tags": [],
  "author": null,
  "internal": false,
  "containerwidget": {
    "xtype": "widgetcontainer",
    "title": "container title vbox",
    "mixins": [
      {
        "name": "verticallayout"
      }
    ],
    "tagName": null,
    "widgetslotTemplate": null,
    "items": [
      {
        "mixins": [],
        "xtype": "widgetwrapper",
        "title": "wrapper",
        "widget": {
          "xtype": "list",
          "title": "Notification Jobs",
          "mixins": [
            {
              "formoptions": {
                "jtype": "notification"
              },
              "name": "crud",
              "form": "jobform"
            },
            {
              "name": "pagination"
            },
            {
              "name": "sortablearray"
            },
            {
              "name": "arraysearch"
            },
            {
              "filters": [],
              "name": "customfilterlist",
              "default_filter": "{\"$or\":[{\"jtype\":{\"$eq\":\"notification\"}}]}"
            }
          ],
          "tagName": null,
          "columnsOrder": [],
          "default_column_sort": {
            "direction": "ASC"
          },
          "useRenderers": true,
          "listed_crecord_type": "job",
          "displayed_columns": [
            "task",
            "start",
            "rrule",
            "last_execution",
            "jtype"
          ],
          "contentTruncatedLength": 150,
          "id": "list_738ebc03-bb14-0e51-8046-460451026e1f",
          "_id": "list_738ebc03-bb14-0e51-8046-460451026e1f"
        },
        "id": "widgetwrapper_e19b70e5-5e77-4031-150b-1e6326547874",
        "_id": "widgetwrapper_e19b70e5-5e77-4031-150b-1e6326547874"
      }
    ],
    "id": "widgetcontainer_846315ad-c2c2-c152-b2d0-ea8f14a3b092",
    "_id": "widgetcontainer_846315ad-c2c2-c152-b2d0-ea8f14a3b092"
  },
  "id": "view_notifications",
  "_id": "view_notifications"
}